pytest_qt_app.py
pytest_qt_app-1.8.0.dist-info/METADATA
pytest_qt_app-1.8.0.dist-info/WHEEL
pytest_qt_app-1.8.0.dist-info/entry_points.txt
pytest_qt_app-1.8.0.dist-info/top_level.txt
pytest_qt_app-1.8.0.dist-info/RECORD
